onilock/__init__.py
onilock/account_manager.py
onilock/core/__init__.py
onilock/core/constants.py
onilock/core/decorators.py
onilock/core/encryption/__init__.py
onilock/core/encryption/encryption.py
onilock/core/enums.py
onilock/core/env.py
onilock/core/exceptions/__init__.py
onilock/core/exceptions/exceptions.py
onilock/core/gpg.py
onilock/core/keystore.py
onilock/core/logging_manager.py
onilock/core/settings.py
onilock/core/utils.py
onilock/db/__init__.py
onilock/db/database_manager.py
onilock/db/engines.py
onilock/db/migrations/__init__.py
onilock/db/migrations/migrations.py
onilock/db/models.py
onilock/filemanager.py
onilock/run.py
onilock-1.7.1.dist-info/LICENSE
onilock-1.7.1.dist-info/METADATA
onilock-1.7.1.dist-info/WHEEL
onilock-1.7.1.dist-info/entry_points.txt
onilock-1.7.1.dist-info/RECORD
