Metadata-Version: 2.3
Name: onilock
Version: 1.7.1
Summary: Password Manager CLI
Author: Mouad Kommir
Author-email: mouadkommir@gmail.com
Requires-Python: >=3.10
Classifier: Development Status :: 4 - Beta
Classifier: License :: OSI Approved :: Apache Software License
Classifier: Operating System :: MacOS :: MacOS X
Classifier: Operating System :: POSIX :: Linux
Classifier: Programming Language :: Python :: 3
Classifier: Programming Language :: Python :: 3.10
Classifier: Programming Language :: Python :: 3.11
Classifier: Programming Language :: Python :: 3.12
Classifier: Programming Language :: Python :: 3.13
Classifier: Topic :: Security :: Cryptography
Classifier: Topic :: Software Development :: Libraries :: Python Modules
Requires-Dist: bcrypt (>=4.2.1,<5.0.0)
Requires-Dist: colorlog (>=6.9.0,<7.0.0)
Requires-Dist: cryptography (>=44.0.1,<45.0.0)
Requires-Dist: keyring (>=25.6.0,<26.0.0)
Requires-Dist: pycryptodome (>=3.21.0,<4.0.0)
Requires-Dist: pydantic-settings (>=2.7.1,<3.0.0)
Requires-Dist: pyperclip (>=1.9.0,<2.0.0)
Requires-Dist: python-gnupg (>=0.5.4,<0.6.0)
Requires-Dist: typer (>=0.15.1,<0.16.0)
Project-URL: Homepage, https://github.com/aiokaizen/onilock
Project-URL: Issues, https://github.com/aiokaizen/onilock/issues
